setup.py
privat/__init__.py
privat/app.py
privat/curses.py
privat/engine.py
privat/io.py
privatizace.egg-info/PKG-INFO
privatizace.egg-info/SOURCES.txt
privatizace.egg-info/dependency_links.txt
privatizace.egg-info/entry_points.txt
privatizace.egg-info/top_level.txt