Metadata-Version: 1.1
Name: privatizace
Version: 0.1.0
Summary: Logical game, a homage to the old game Velká privatizace
Home-page: https://github.com/garncarz/privatizace
Author: Ondřej Garncarz
Author-email: ondrej@garncarz.cz
License: MIT
Keywords: game logical
Platform: UNKNOWN
Classifier: Development Status :: 3 - Alpha
Classifier: Environment :: Console :: Curses
Classifier: License :: OSI Approved :: MIT License
Classifier: Operating System :: POSIX
Classifier: Programming Language :: Python :: 3.5
Classifier: Topic :: Games/Entertainment :: Board Games
